lottie_animation_manager/__init__.py
lottie_animation_manager/__main__.py
lottie_animation_manager/utils.py
lottie_animation_manager-0.0.5.dist-info/LICENSE.txt
lottie_animation_manager-0.0.5.dist-info/METADATA
lottie_animation_manager-0.0.5.dist-info/WHEEL
lottie_animation_manager-0.0.5.dist-info/entry_points.txt
lottie_animation_manager-0.0.5.dist-info/top_level.txt
lottie_animation_manager-0.0.5.dist-info/RECORD
