Metadata-Version: 2.1
Name: lottie-animation-manager
Version: 0.0.5
Summary: The easiest way to manage, compress, and upload Lottie assets to a CDN.
Home-page: https://github.com/bakztfuture/lottie_animation_manager
Author: Bakz T. Future
Author-email: bakztfuture@gmail.com
License: UNKNOWN
Keywords: lottie animations bodymovin cloudfront cdn
Platform: UNKNOWN
Classifier: Development Status :: 3 - Alpha
Classifier: Programming Language :: Python :: 3
Classifier: License :: OSI Approved :: MIT License
Classifier: Operating System :: OS Independent
Requires-Python: >=3.6
Requires-Dist: boto (>=2.49)
Requires-Dist: click (>=7.1)
Requires-Dist: colorama (>=0.4)
Requires-Dist: emoji (>=0.5)
Requires-Dist: pyfiglet (>=0.8)
Requires-Dist: tinify (>=1.5)
